parallelmap/__init__.py
parallelmap/wrappers/__init__.py
parallelmap/wrappers/data_wrapper.py
parallelmap-0.0.1.dist-info/LICENSE
parallelmap-0.0.1.dist-info/METADATA
parallelmap-0.0.1.dist-info/WHEEL
parallelmap-0.0.1.dist-info/top_level.txt
parallelmap-0.0.1.dist-info/RECORD
